keios_protocol_classification_class2/__init__.py
keios_protocol_classification_class2/flatbuffers/ClassificationClass2Request.py
keios_protocol_classification_class2/flatbuffers/ClassificationClass2Response.py
keios_protocol_classification_class2/flatbuffers/Probability.py
keios_protocol_classification_class2/flatbuffers/Vector.py
keios_protocol_classification_class2-1.0.0.dist-info/WHEEL
keios_protocol_classification_class2-1.0.0.dist-info/METADATA
keios_protocol_classification_class2-1.0.0.dist-info/RECORD
